MANIFEST.in
README.rst
setup.py
ogb_lite/__init__.py
ogb_lite/version.py
ogb_lite.egg-info/PKG-INFO
ogb_lite.egg-info/SOURCES.txt
ogb_lite.egg-info/dependency_links.txt
ogb_lite.egg-info/requires.txt
ogb_lite.egg-info/top_level.txt
ogb_lite/graphproppred/__init__.py
ogb_lite/graphproppred/dataset.py
ogb_lite/graphproppred/make_master_file.py
ogb_lite/graphproppred/master.csv
ogb_lite/io/__init__.py
ogb_lite/io/read_graph_raw.py
ogb_lite/io/save_dataset.py
ogb_lite/linkproppred/__init__.py
ogb_lite/linkproppred/dataset.py
ogb_lite/linkproppred/make_master_file.py
ogb_lite/linkproppred/master.csv
ogb_lite/lsc/__init__.py
ogb_lite/lsc/pcqm4m.py
ogb_lite/nodeproppred/__init__.py
ogb_lite/nodeproppred/dataset.py
ogb_lite/nodeproppred/make_master_file.py
ogb_lite/nodeproppred/master.csv
ogb_lite/utils/__init__.py
ogb_lite/utils/features.py
ogb_lite/utils/mol.py
ogb_lite/utils/numpy_util.py
ogb_lite/utils/pickle_util.py
ogb_lite/utils/url.py