Metadata-Version: 2.1
Name: ogb-lite
Version: 0.0.3
Summary: Open Graph Benchmark Lite (ogb_lite) is a subset of the ogb project. It supports library-agnostic loaders and it does not require torch.
Home-page: https://github.com/CrawlScript/ogb_lite
Author: Jun Hu
Author-email: hujunxianligong@gmail.com
License: MIT
Keywords: pytorch,graph machine learning,graph representation learning,graph neural networks
Platform: UNKNOWN
Provides-Extra: torch
